scanwalk.py
scanwalk-0.0.5.dist-info/LICENSE
scanwalk-0.0.5.dist-info/METADATA
scanwalk-0.0.5.dist-info/WHEEL
scanwalk-0.0.5.dist-info/top_level.txt
scanwalk-0.0.5.dist-info/RECORD
