Metadata-Version: 2.1
Name: scanwalk
Version: 0.0.5
Summary: Walk directories trees with os.scandir, generating DirEntry objects
Home-page: https://github.com/moreati/scanwalk
Author: Alex Willmer
Author-email: alex@moreati.org.uk
License: MIT
Classifier: Development Status :: 3 - Alpha
Classifier: Intended Audience :: Developers
Classifier: License :: OSI Approved :: MIT License
Classifier: Programming Language :: Python :: 3
Classifier: Programming Language :: Python :: 3 :: Only
Classifier: Programming Language :: Python :: 3.7
Classifier: Programming Language :: Python :: 3.8
Classifier: Programming Language :: Python :: 3.9
Classifier: Programming Language :: Python :: 3.10
Classifier: Programming Language :: Python :: Implementation :: CPython
Classifier: Programming Language :: Python :: Implementation :: PyPy
Classifier: Typing :: Typed
Requires-Python: >=3.7
License-File: LICENSE
